{
    "author-md": "WG14",
    "comments": [
        {
            "author-md": "WG14",
            "date": "2013-10-03",
            "filename": "1.md"
        }
    ],
    "conversion-src": [
        "n2396.htm"
    ],
    "crossref": [],
    "date": "2012-10-08",
    "reference-doc-md": "[N1653](https://www.open-std.org/jtc1/sc22/wg14/www/docs/n1653.htm)",
    "status": "closed",
    "submitted-against": "c11c17",
    "submitter-md": "Jens Gustedt",
    "summary-md": "no specification for the access to variables with temporary lifetime",
    "x-dr-summary-md": "no specification for the access to variables with temporary lifetime",
    "x-dr-version-date": "10/2013",
    "x-orig-status-class": "closed",
    "x-table-summary-md": "no specification for the access to variables with temporary storage"
}