{
    "authors-md": [
        "Clive D.W. Feather",
        "BSI"
    ],
    "comments": [],
    "conversion-src": [
        "dr.htm",
        "dr_176.html"
    ],
    "crossref": [],
    "date": "1995-10-16",
    "status": "closed",
    "submitted-against": "c90",
    "summary-md": "Are rules concerning whether `#error` generates a diagnostic contradictory?",
    "x-author-md": "Clive D.W. Feather",
    "x-orig-summary-md": "Are rules concerning whether `#error` generates a diagnostic contradictory?",
    "x-submitter-md": "BSI",
    "x-summary-author-md": "Clive Feather"
}