{
    "authors-md": [
        "WG 14",
        "Fred J. Tydeman"
    ],
    "comments": [
        {
            "author-md": "WG14",
            "date": "2017-11-03",
            "filename": "1.md"
        }
    ],
    "conversion-src": [
        "n2396.htm"
    ],
    "crossref": [],
    "date": "2013-01-07",
    "fixed-in": [
        "c17"
    ],
    "reference-doc-md": "[N1670](https://www.open-std.org/jtc1/sc22/wg14/www/docs/n1670.htm)",
    "status": "fixed",
    "submitted-against": "c11c17",
    "summary-md": "G.5.1: `-yv` and `-x/v` are ambiguous",
    "x-author-md": "WG 14",
    "x-dr-summary-md": "G.5.1: -yv and -x/v are ambiguous",
    "x-dr-version-date": "10/2017",
    "x-orig-status-class": "c17",
    "x-submitter-md": "Fred J. Tydeman",
    "x-table-summary-md": "G.5.1: `-yv` and `-x/v` are ambiguous"
}