{
    "authors-md": [
        "Larry Jones",
        "Project Editor (P.J. Plauger)"
    ],
    "comments": [
        {
            "author-md": "WG14",
            "date": "1997-09-23",
            "filename": "1.md"
        }
    ],
    "conversion-src": [
        "dr.htm",
        "dr_139.html"
    ],
    "crossref": [
        "0059",
        "0088"
    ],
    "date": "1994-06-13",
    "fixed-in": [
        "c90tc2"
    ],
    "status": "fixed",
    "submitted-against": "c90",
    "summary-md": "Is an incomplete type compatible with the completed type?",
    "x-author-md": "Larry Jones",
    "x-orig-summary-md": "Is an incomplete type compatible with the completed type? See [Defect Report #059](issue:0059)",
    "x-submitter-md": "Project Editor (P.J. Plauger)",
    "x-summary-author-md": "Larry Jones"
}